{
    "Ar36": {
        "error": 0.00021189402335290483,
        "error_type": "SEM",
        "filter_outliers_dict": {
            "filter_outliers": true,
            "iterations": 1,
            "std_devs": 3,
            "use_iqr_filtering": false,
            "use_standard_deviation_filtering": false
        },
        "fit": "linear",
        "fn": 339,
        "include_baseline_error": true,
        "n": 340,
        "outlier_excluded": [
            263
        ],
        "reviewed": true,
        "user_excluded": [],
        "value": 0.016189978044596605
    },
    "Ar37": {
        "error": 0.01623787245889634,
        "error_type": "SEM",
        "filter_outliers_dict": {
            "filter_outliers": true,
            "iterations": 1,
            "std_devs": 3,
            "use_iqr_filtering": false,
            "use_standard_deviation_filtering": false
        },
        "fit": "linear",
        "fn": 339,
        "include_baseline_error": true,
        "n": 340,
        "outlier_excluded": [
            149
        ],
        "reviewed": true,
        "user_excluded": [],
        "value": 6.598988967925443
    },
    "Ar38": {
        "error": 0.005547930247987326,
        "error_type": "SEM",
        "filter_outliers_dict": {
            "filter_outliers": true,
            "iterations": 1,
            "std_devs": 3,
            "use_iqr_filtering": false,
            "use_standard_deviation_filtering": false
        },
        "fit": "linear",
        "fn": 339,
        "include_baseline_error": true,
        "n": 340,
        "outlier_excluded": [
            126
        ],
        "reviewed": true,
        "user_excluded": [],
        "value": -0.03612979928658454
    },
    "Ar39": {
        "error": 0.007784209359337047,
        "error_type": "SEM",
        "filter_outliers_dict": {
            "filter_outliers": true,
            "iterations": 1,
            "std_devs": 3,
            "use_iqr_filtering": false,
            "use_standard_deviation_filtering": false
        },
        "fit": "linear",
        "fn": 339,
        "include_baseline_error": true,
        "n": 340,
        "outlier_excluded": [
            297
        ],
        "reviewed": true,
        "user_excluded": [],
        "value": 1.4272764409749565
    },
    "Ar40": {
        "error": 0.027704948330160302,
        "error_type": "SEM",
        "filter_outliers_dict": {
            "filter_outliers": true,
            "iterations": 1,
            "std_devs": 3,
            "use_iqr_filtering": false,
            "use_standard_deviation_filtering": false
        },
        "fit": "parabolic",
        "fn": 339,
        "include_baseline_error": true,
        "n": 340,
        "outlier_excluded": [
            3
        ],
        "reviewed": true,
        "user_excluded": [],
        "value": 8.502790921066788
    }
}